{
  "project_info": {
    "project_number": "734896604768",
    "project_id": "expense-86a63",
    "storage_bucket": "expense-86a63.firebasestorage.app"
  },
  "client": [
    {
      "client_info": {
        "mobilesdk_app_id": "1:734896604768:android:a049af689a01a6bed36505",
        "android_client_info": {
          "package_name": "com.example.expense_tracker"
        }
      },
      "oauth_client": [],
      "api_key": [
        {
          "current_key": "AIzaSyB98ZTDitIfPqq4S6Cjko_XhCSoTg07vpk"
        }
      ],
      "services": {
        "appinvite_service": {
          "other_platform_oauth_client": []
        }
      }
    }
  ],
  "configuration_version": "1"
}